{
  "status": true,
  "data": [
    {
      "id": "65",
      "name": "Comic video",
      "category": "Мультики",
      "picture": "https://www.dropbox.com/s/e0uhdna62y0r8g4/den-zaschity-detei.jpg?raw=1",
      "video": "https://www.dropbox.com/s/x1lev14gaufnxlz/%D0%BE%D0%B1%D1%83%D1%87%D0%B0%D1%8E%D1%89%D0%B5%D0%B5%20%D0%B4%D0%B5%D1%82%D1%8F%D0%BC%20%20%D0%9C%D1%83%D0%BB%D1%8C%D1%82%D0%B8%D0%BA%20%D0%BF%D1%80%D0%BE%20%D0%AD%D0%BA%D1%81%D0%BA%D0%B0%D0%B2%D0%B0%D1%82%D0%BE%D1%80%20%D0%9C%D0%B0%D1%81%D1%8E_%20%D0%92%D0%B5%D1%81%D0%B5%D0%BB%D0%B0%D1%8F%20%D0%9A%D0%B0%D1%80%D1%83%D1%81%D0%B5%D0%BB%D1%8C%20-%20%D0%9E%D0%B4%D0%B5%D0%B6%D0%B4%D0%B0.mp4?raw=1",
      "description": "обучающее детям  Мультик про Экскаватор Масю и Веселая Карусель - Одежда"
    },
    {
      "id": "66",
      "name": "Funny video",
      "category": "Мультики",
      "picture": "https://www.dropbox.com/s/nb1dt4umft5imyy/1512492951_doshkolnoe-obrazovanie.jpg?raw=1",
      "video": "https://www.dropbox.com/s/s8emx0301mxtiev/%D0%BE%D0%B1%D1%83%D1%87%D0%B0%D1%8E%D1%89%D0%B5%D0%B5%20%D0%B4%D0%B5%D1%82%D1%8F%D0%BC%20Bath%20Song%20_%20ABCkidTV%20Nursery%20Rhymes%20%26%20Kids%20Songs.mp4?raw=1",
      "description": "\"Песенки для детей про купание в ванной\""
    },
    {
      "id": "67",
      "name": "Random",
      "category": "Мультики",
      "picture": "https://www.dropbox.com/s/83b0s8moayauq13/e364002caca49e1051b3d1603342c6565776ad91.jpg?raw=1",
      "video": "https://www.dropbox.com/s/heo59g9y496136f/%D0%BE%D0%B1%D1%83%D1%87%D0%B0%D1%8E%D1%89%D0%B5%D0%B5%20%D0%B4%D0%B5%D1%82%D1%8F%D0%BC.mp4?raw=1",
      "description": "обучающее видео  детям"
    },
    {
      "id": "68",
      "name": "Example",
      "category": "Мультики",
      "picture": "https://www.dropbox.com/s/y2y6x9a3xlfdjjm/thinking-happy-kid-idea-bulb-above-head-72876206.jpg?raw=1",
      "video": "https://www.dropbox.com/s/22gsick5yt0jpb9/%D0%BE%D0%B1%D1%83%D1%87%D0%B0%D1%8E%D1%89%D0%B5%D0%B5%20%D0%B4%D0%B5%D1%82%D1%8F%D0%BC%29%20videoplayback.mp4?raw=1",
      "description": "детские развивающие мультики"
    }
  ]
}
